LICENSE.txt
README.md
setup.cfg
setup.py
./packname/__init__.py
./packname/pack.py
./packname/subm_a/__init__.py
./packname/subm_a/subm_a_class_01.py
./packname/subm_a/subm_a_class_02.py
./packname/subm_b/__init__.py
./packname/subm_b/subm_b_class_01.py
./packname/subm_b/subm_b_class_02.py
packname/__init__.py
packname.egg-info/PKG-INFO
packname.egg-info/SOURCES.txt
packname.egg-info/dependency_links.txt
packname.egg-info/requires.txt
packname.egg-info/top_level.txt
packname/subm_a/__init__.py
packname/subm_a/subm_a_class_01.py
packname/subm_a/subm_a_class_02.py
packname/subm_b/__init__.py
packname/subm_b/subm_b_class_01.py
packname/subm_b/subm_b_class_02.py