Metadata-Version: 2.1
Name: packname
Version: 1.2.8
Summary: blablabla
Home-page: https://github.com/fgabbaninililly/TestPyPiUpload
Author: Fra
Author-email: your.email@domain.com
License: MIT
Download-URL: https://github.com/fgabbaninililly/TestPyPiUpload/archive/refs/tags/1.2.5.tar.gz
Keywords: SOME,MEANINGFULL,KEYWORDS
Platform: UNKNOWN
Classifier: Development Status :: 3 - Alpha
Classifier: Intended Audience :: Developers
Classifier: Topic :: Software Development :: Build Tools
Classifier: License :: OSI Approved :: MIT License
Classifier: Programming Language :: Python :: 3
Classifier: Programming Language :: Python :: 3.4
Classifier: Programming Language :: Python :: 3.5
Classifier: Programming Language :: Python :: 3.6
Requires-Python: >=3.6
License-File: LICENSE.txt
